CHANGELOG.txt
LICENSE
MANIFEST.in
README.md
pyproject.toml
setup.py
test.py
PhysiPy/__init__.py
PhysiPy/constants.py
PhysiPy/derivations.py
PhysiPy/equations.py
PhysiPy.egg-info/SOURCES.txt
PhysiPy.egg-info/dependency_links.txt
PhysiPy.egg-info/top_level.txt
PhysiPy_Python.egg-info/PKG-INFO
PhysiPy_Python.egg-info/SOURCES.txt
PhysiPy_Python.egg-info/dependency_links.txt
PhysiPy_Python.egg-info/requires.txt
PhysiPy_Python.egg-info/top_level.txt