Metadata-Version: 2.1
Name: PhysiPy-Python
Version: 1.0.1
Summary: Python Library to Solve Physics Equations
Home-page: https://github.com/rohankishore/PhysiPy
Author: Rohan Kishore
Author-email: rohankishore746@gmail.com
License: MIT
Keywords: calculator
Classifier: Development Status :: 5 - Production/Stable
Classifier: Intended Audience :: Education
Classifier: Operating System :: Microsoft :: Windows :: Windows 11
Classifier: License :: OSI Approved :: MIT License
Classifier: Programming Language :: Python :: 3
License-File: LICENSE
